[
    {
        "RelativeTime":233.67,
        "H2 Node":"6.00",
        "H2 Set-Point":"945.00",
        "H2 Actual Flow":945.11,
        "N2 Node":"4.00",
        "N2 Set-Point":"315.00",
        "N2 Actual Flow":315.45,
        "T Reactor (sliding TC)":"990.00",
        "T Heater 1":398.66,
        "SP Heater 1":"250.00",
        "nan":398.66,
        "nan":250.0,
        "Pressure setpoint":100.0,
        "N2 poisoning set-point":0.0,
        "N2 poisoning Actual flow":"0.00",
        "H2 Uncontrolled flow":"0.00",
        "N2 Uncontrolled flow":"0.00",
        "Inlet calc. flowrate":"28.70",
        "Outlet meas.flowrate":"32.48",
        "Pressure reading":"76.39",
        "T14":"404.61",
        "T13":"406.06",
        "T12":"407.14",
        "T11":"408.67",
        "T10":"411.41",
        "T9":"414.54",
        "T8":"419.86",
        "T7":"426.65",
        "T6":"432.67",
        "T5":"434.08",
        "T4":"431.52",
        "T3":"429.58",
        "T2":"425.62",
        "T1":"421.86",
        "nan":null,
        "Date":"2025-02-22T07:17:20",
        "Stage":57,
        "File":"Exp003_R150_#2674_7949",
        "RT (sec)":19.21,
        "Area":15263,
        "H2":70.0,
        "RT (sec)       _1":21.97,
        "Area           _2":225886,
        "N2":21.838,
        "RT (sec)       _3":37.82,
        "Area           _4":349404,
        "NH3":15.15,
        "Sample name":"Stream 2 - R150"
    },
    {
        "RelativeTime":537.68,
        "H2 Node":"6.00",
        "H2 Set-Point":"945.00",
        "H2 Actual Flow":945.0,
        "N2 Node":"4.00",
        "N2 Set-Point":"315.00",
        "N2 Actual Flow":315.31,
        "T Reactor (sliding TC)":"990.00",
        "T Heater 1":393.94,
        "SP Heater 1":"250.00",
        "nan":393.94,
        "nan":250.0,
        "Pressure setpoint":100.01,
        "N2 poisoning set-point":0.0,
        "N2 poisoning Actual flow":"0.00",
        "H2 Uncontrolled flow":"0.00",
        "N2 Uncontrolled flow":"0.00",
        "Inlet calc. flowrate":"28.68",
        "Outlet meas.flowrate":"32.63",
        "Pressure reading":"76.39",
        "T14":"401.42",
        "T13":"402.82",
        "T12":"403.85",
        "T11":"405.36",
        "T10":"408.00",
        "T9":"411.06",
        "T8":"416.36",
        "T7":"423.10",
        "T6":"429.07",
        "T5":"430.41",
        "T4":"427.87",
        "T3":"425.97",
        "T2":"422.09",
        "T1":"418.39",
        "nan":null,
        "Date":"2025-02-22T07:22:24",
        "Stage":57,
        "File":"Exp003_R150_#2674_7950",
        "RT (sec)":19.21,
        "Area":15311,
        "H2":70.0,
        "RT (sec)       _1":21.97,
        "Area           _2":226921,
        "N2":21.938,
        "RT (sec)       _3":37.84,
        "Area           _4":337907,
        "NH3":14.651,
        "Sample name":"Stream 2 - R150"
    },
    {
        "RelativeTime":841.66,
        "H2 Node":"6.00",
        "H2 Set-Point":"945.00",
        "H2 Actual Flow":945.0,
        "N2 Node":"4.00",
        "N2 Set-Point":"315.00",
        "N2 Actual Flow":315.38,
        "T Reactor (sliding TC)":"990.00",
        "T Heater 1":388.87,
        "SP Heater 1":"250.00",
        "nan":388.87,
        "nan":250.0,
        "Pressure setpoint":100.03,
        "N2 poisoning set-point":0.0,
        "N2 poisoning Actual flow":"0.00",
        "H2 Uncontrolled flow":"0.00",
        "N2 Uncontrolled flow":"0.00",
        "Inlet calc. flowrate":"28.69",
        "Outlet meas.flowrate":"33.09",
        "Pressure reading":"76.40",
        "T14":"397.08",
        "T13":"398.50",
        "T12":"399.51",
        "T11":"400.98",
        "T10":"403.63",
        "T9":"406.65",
        "T8":"411.72",
        "T7":"418.31",
        "T6":"424.20",
        "T5":"425.60",
        "T4":"423.26",
        "T3":"421.45",
        "T2":"417.69",
        "T1":"414.04",
        "nan":null,
        "Date":"2025-02-22T07:27:28",
        "Stage":57,
        "File":"Exp003_R150_#2674_7952",
        "RT (sec)":19.21,
        "Area":15953,
        "H2":71.0,
        "RT (sec)       _1":21.97,
        "Area           _2":226000,
        "N2":21.849,
        "RT (sec)       _3":37.85,
        "Area           _4":333548,
        "NH3":14.462,
        "Sample name":"Stream 2 - R150"
    },
    {
        "RelativeTime":1145.58,
        "H2 Node":"6.00",
        "H2 Set-Point":"945.00",
        "H2 Actual Flow":945.0,
        "N2 Node":"4.00",
        "N2 Set-Point":"315.00",
        "N2 Actual Flow":315.29,
        "T Reactor (sliding TC)":"990.00",
        "T Heater 1":383.8,
        "SP Heater 1":"250.00",
        "nan":383.8,
        "nan":250.0,
        "Pressure setpoint":100.01,
        "N2 poisoning set-point":0.0,
        "N2 poisoning Actual flow":"0.00",
        "H2 Uncontrolled flow":"0.00",
        "N2 Uncontrolled flow":"0.00",
        "Inlet calc. flowrate":"28.68",
        "Outlet meas.flowrate":"32.95",
        "Pressure reading":"76.39",
        "T14":"392.24",
        "T13":"393.61",
        "T12":"394.61",
        "T11":"396.15",
        "T10":"398.66",
        "T9":"401.52",
        "T8":"406.62",
        "T7":"413.04",
        "T6":"418.67",
        "T5":"420.22",
        "T4":"417.99",
        "T3":"416.32",
        "T2":"412.60",
        "T1":"408.98",
        "nan":null,
        "Date":"2025-02-22T07:32:32",
        "Stage":57,
        "File":"Exp003_R150_#2674_7954",
        "RT (sec)":19.21,
        "Area":16203,
        "H2":72.0,
        "RT (sec)       _1":21.97,
        "Area           _2":227165,
        "N2":21.962,
        "RT (sec)       _3":37.87,
        "Area           _4":318331,
        "NH3":13.803,
        "Sample name":"Stream 2 - R150"
    },
    {
        "RelativeTime":1449.67,
        "H2 Node":"6.00",
        "H2 Set-Point":"945.00",
        "H2 Actual Flow":945.03,
        "N2 Node":"4.00",
        "N2 Set-Point":"315.00",
        "N2 Actual Flow":315.41,
        "T Reactor (sliding TC)":"990.00",
        "T Heater 1":378.73,
        "SP Heater 1":"250.00",
        "nan":378.73,
        "nan":250.0,
        "Pressure setpoint":100.02,
        "N2 poisoning set-point":0.0,
        "N2 poisoning Actual flow":"0.00",
        "H2 Uncontrolled flow":"0.00",
        "N2 Uncontrolled flow":"0.00",
        "Inlet calc. flowrate":"28.69",
        "Outlet meas.flowrate":"32.98",
        "Pressure reading":"76.39",
        "T14":"387.32",
        "T13":"388.67",
        "T12":"389.60",
        "T11":"391.09",
        "T10":"393.56",
        "T9":"396.38",
        "T8":"401.38",
        "T7":"407.60",
        "T6":"413.19",
        "T5":"414.68",
        "T4":"412.62",
        "T3":"411.03",
        "T2":"407.31",
        "T1":"403.85",
        "nan":null,
        "Date":"2025-02-22T07:37:36",
        "Stage":57,
        "File":"Exp003_R150_#2674_7956",
        "RT (sec)":19.21,
        "Area":15976,
        "H2":71.0,
        "RT (sec)       _1":21.97,
        "Area           _2":226899,
        "N2":21.936,
        "RT (sec)       _3":37.88,
        "Area           _4":313721,
        "NH3":13.603,
        "Sample name":"Stream 2 - R150"
    },
    {
        "RelativeTime":1753.67,
        "H2 Node":"6.00",
        "H2 Set-Point":"945.00",
        "H2 Actual Flow":945.09,
        "N2 Node":"4.00",
        "N2 Set-Point":"315.00",
        "N2 Actual Flow":315.3,
        "T Reactor (sliding TC)":"990.00",
        "T Heater 1":373.67,
        "SP Heater 1":"250.00",
        "nan":373.67,
        "nan":250.0,
        "Pressure setpoint":100.01,
        "N2 poisoning set-point":0.0,
        "N2 poisoning Actual flow":"0.00",
        "H2 Uncontrolled flow":"0.00",
        "N2 Uncontrolled flow":"0.00",
        "Inlet calc. flowrate":"28.68",
        "Outlet meas.flowrate":"32.82",
        "Pressure reading":"76.39",
        "T14":"382.17",
        "T13":"383.53",
        "T12":"384.42",
        "T11":"385.86",
        "T10":"388.20",
        "T9":"391.06",
        "T8":"395.78",
        "T7":"401.85",
        "T6":"407.33",
        "T5":"408.92",
        "T4":"406.93",
        "T3":"405.47",
        "T2":"401.99",
        "T1":"398.54",
        "nan":null,
        "Date":"2025-02-22T07:42:40",
        "Stage":57,
        "File":"Exp003_R150_#2674_7957",
        "RT (sec)":19.22,
        "Area":16211,
        "H2":72.0,
        "RT (sec)       _1":21.97,
        "Area           _2":227874,
        "N2":22.03,
        "RT (sec)       _3":37.92,
        "Area           _4":303140,
        "NH3":13.144,
        "Sample name":"Stream 2 - R150"
    },
    {
        "RelativeTime":2057.77,
        "H2 Node":"6.00",
        "H2 Set-Point":"945.00",
        "H2 Actual Flow":945.08,
        "N2 Node":"4.00",
        "N2 Set-Point":"315.00",
        "N2 Actual Flow":315.17,
        "T Reactor (sliding TC)":"990.00",
        "T Heater 1":368.6,
        "SP Heater 1":"250.00",
        "nan":368.6,
        "nan":250.0,
        "Pressure setpoint":100.01,
        "N2 poisoning set-point":0.0,
        "N2 poisoning Actual flow":"0.00",
        "H2 Uncontrolled flow":"0.00",
        "N2 Uncontrolled flow":"0.00",
        "Inlet calc. flowrate":"28.67",
        "Outlet meas.flowrate":"32.92",
        "Pressure reading":"76.39",
        "T14":"377.06",
        "T13":"378.38",
        "T12":"379.21",
        "T11":"380.60",
        "T10":"382.91",
        "T9":"385.62",
        "T8":"390.12",
        "T7":"395.97",
        "T6":"401.31",
        "T5":"402.98",
        "T4":"401.17",
        "T3":"399.82",
        "T2":"396.45",
        "T1":"393.12",
        "nan":null,
        "Date":"2025-02-22T07:47:44",
        "Stage":57,
        "File":"Exp003_R150_#2674_7959",
        "RT (sec)":19.22,
        "Area":16360,
        "H2":72.0,
        "RT (sec)       _1":21.97,
        "Area           _2":228922,
        "N2":22.131,
        "RT (sec)       _3":37.95,
        "Area           _4":288364,
        "NH3":12.503,
        "Sample name":"Stream 2 - R150"
    },
    {
        "RelativeTime":2361.65,
        "H2 Node":"6.00",
        "H2 Set-Point":"945.00",
        "H2 Actual Flow":944.95,
        "N2 Node":"4.00",
        "N2 Set-Point":"315.00",
        "N2 Actual Flow":315.48,
        "T Reactor (sliding TC)":"990.00",
        "T Heater 1":363.53,
        "SP Heater 1":"250.00",
        "nan":363.53,
        "nan":250.0,
        "Pressure setpoint":100.03,
        "N2 poisoning set-point":0.0,
        "N2 poisoning Actual flow":"0.00",
        "H2 Uncontrolled flow":"0.00",
        "N2 Uncontrolled flow":"0.00",
        "Inlet calc. flowrate":"28.70",
        "Outlet meas.flowrate":"33.29",
        "Pressure reading":"76.39",
        "T14":"371.87",
        "T13":"373.27",
        "T12":"373.96",
        "T11":"375.36",
        "T10":"377.56",
        "T9":"380.27",
        "T8":"384.56",
        "T7":"390.16",
        "T6":"395.26",
        "T5":"396.94",
        "T4":"395.30",
        "T3":"394.08",
        "T2":"390.79",
        "T1":"387.60",
        "nan":null,
        "Date":"2025-02-22T07:52:48",
        "Stage":57,
        "File":"Exp003_R150_#2674_7961",
        "RT (sec)":19.22,
        "Area":16648,
        "H2":73.0,
        "RT (sec)       _1":21.97,
        "Area           _2":229623,
        "N2":22.199,
        "RT (sec)       _3":37.98,
        "Area           _4":275091,
        "NH3":11.928,
        "Sample name":"Stream 2 - R150"
    },
    {
        "RelativeTime":2665.69,
        "H2 Node":"6.00",
        "H2 Set-Point":"945.00",
        "H2 Actual Flow":945.01,
        "N2 Node":"4.00",
        "N2 Set-Point":"315.00",
        "N2 Actual Flow":315.58,
        "T Reactor (sliding TC)":"990.00",
        "T Heater 1":358.46,
        "SP Heater 1":"250.00",
        "nan":358.46,
        "nan":250.0,
        "Pressure setpoint":100.01,
        "N2 poisoning set-point":0.0,
        "N2 poisoning Actual flow":"0.00",
        "H2 Uncontrolled flow":"0.00",
        "N2 Uncontrolled flow":"0.00",
        "Inlet calc. flowrate":"28.71",
        "Outlet meas.flowrate":"32.54",
        "Pressure reading":"76.39",
        "T14":"366.69",
        "T13":"367.95",
        "T12":"368.76",
        "T11":"370.12",
        "T10":"372.20",
        "T9":"374.65",
        "T8":"378.91",
        "T7":"384.28",
        "T6":"389.26",
        "T5":"391.02",
        "T4":"389.45",
        "T3":"388.38",
        "T2":"385.21",
        "T1":"382.14",
        "nan":null,
        "Date":"2025-02-22T07:57:52",
        "Stage":57,
        "File":"Exp003_R150_#2674_7962",
        "RT (sec)":19.22,
        "Area":16502,
        "H2":73.0,
        "RT (sec)       _1":21.97,
        "Area           _2":230646,
        "N2":22.298,
        "RT (sec)       _3":37.99,
        "Area           _4":267706,
        "NH3":11.608,
        "Sample name":"Stream 2 - R150"
    },
    {
        "RelativeTime":2969.64,
        "H2 Node":"6.00",
        "H2 Set-Point":"945.00",
        "H2 Actual Flow":944.97,
        "N2 Node":"4.00",
        "N2 Set-Point":"315.00",
        "N2 Actual Flow":315.15,
        "T Reactor (sliding TC)":"990.00",
        "T Heater 1":353.4,
        "SP Heater 1":"250.00",
        "nan":353.4,
        "nan":250.0,
        "Pressure setpoint":100.01,
        "N2 poisoning set-point":0.0,
        "N2 poisoning Actual flow":"0.00",
        "H2 Uncontrolled flow":"0.00",
        "N2 Uncontrolled flow":"0.00",
        "Inlet calc. flowrate":"28.67",
        "Outlet meas.flowrate":"32.98",
        "Pressure reading":"76.39",
        "T14":"361.42",
        "T13":"362.60",
        "T12":"363.48",
        "T11":"364.80",
        "T10":"366.92",
        "T9":"369.28",
        "T8":"373.23",
        "T7":"378.39",
        "T6":"383.08",
        "T5":"384.81",
        "T4":"383.49",
        "T3":"382.49",
        "T2":"379.50",
        "T1":"376.52",
        "nan":null,
        "Date":"2025-02-22T08:02:56",
        "Stage":57,
        "File":"Exp003_R150_#2674_7964",
        "RT (sec)":19.21,
        "Area":16505,
        "H2":73.0,
        "RT (sec)       _1":21.96,
        "Area           _2":229737,
        "N2":22.21,
        "RT (sec)       _3":38.02,
        "Area           _4":251764,
        "NH3":10.916,
        "Sample name":"Stream 2 - R150"
    },
    {
        "RelativeTime":3273.67,
        "H2 Node":"6.00",
        "H2 Set-Point":"945.00",
        "H2 Actual Flow":945.03,
        "N2 Node":"4.00",
        "N2 Set-Point":"315.00",
        "N2 Actual Flow":315.27,
        "T Reactor (sliding TC)":"990.00",
        "T Heater 1":348.33,
        "SP Heater 1":"250.00",
        "nan":348.33,
        "nan":250.0,
        "Pressure setpoint":100.02,
        "N2 poisoning set-point":0.0,
        "N2 poisoning Actual flow":"0.00",
        "H2 Uncontrolled flow":"0.00",
        "N2 Uncontrolled flow":"0.00",
        "Inlet calc. flowrate":"28.68",
        "Outlet meas.flowrate":"32.89",
        "Pressure reading":"76.39",
        "T14":"356.26",
        "T13":"357.57",
        "T12":"358.14",
        "T11":"359.39",
        "T10":"361.43",
        "T9":"363.79",
        "T8":"367.53",
        "T7":"372.37",
        "T6":"376.89",
        "T5":"378.72",
        "T4":"377.43",
        "T3":"376.58",
        "T2":"373.76",
        "T1":"370.93",
        "nan":null,
        "Date":"2025-02-22T08:08:00",
        "Stage":57,
        "File":"Exp003_R150_#2674_7966",
        "RT (sec)":19.21,
        "Area":16593,
        "H2":73.0,
        "RT (sec)       _1":21.96,
        "Area           _2":230718,
        "N2":22.305,
        "RT (sec)       _3":38.06,
        "Area           _4":235803,
        "NH3":10.224,
        "Sample name":"Stream 2 - R150"
    },
    {
        "RelativeTime":3577.67,
        "H2 Node":"6.00",
        "H2 Set-Point":"945.00",
        "H2 Actual Flow":944.98,
        "N2 Node":"4.00",
        "N2 Set-Point":"315.00",
        "N2 Actual Flow":315.32,
        "T Reactor (sliding TC)":"990.00",
        "T Heater 1":343.26,
        "SP Heater 1":"250.00",
        "nan":343.26,
        "nan":250.0,
        "Pressure setpoint":100.01,
        "N2 poisoning set-point":0.0,
        "N2 poisoning Actual flow":"0.00",
        "H2 Uncontrolled flow":"0.00",
        "N2 Uncontrolled flow":"0.00",
        "Inlet calc. flowrate":"28.69",
        "Outlet meas.flowrate":"32.84",
        "Pressure reading":"76.39",
        "T14":"351.03",
        "T13":"352.17",
        "T12":"352.88",
        "T11":"354.05",
        "T10":"355.94",
        "T9":"358.02",
        "T8":"361.70",
        "T7":"366.26",
        "T6":"370.60",
        "T5":"372.42",
        "T4":"371.35",
        "T3":"370.66",
        "T2":"367.84",
        "T1":"365.18",
        "nan":null,
        "Date":"2025-02-22T08:13:04",
        "Stage":57,
        "File":"Exp003_R150_#2674_7967",
        "RT (sec)":19.21,
        "Area":16676,
        "H2":73.0,
        "RT (sec)       _1":21.96,
        "Area           _2":231519,
        "N2":22.382,
        "RT (sec)       _3":38.08,
        "Area           _4":227441,
        "NH3":9.862,
        "Sample name":"Stream 2 - R150"
    },
    {
        "RelativeTime":3881.66,
        "H2 Node":"6.00",
        "H2 Set-Point":"945.00",
        "H2 Actual Flow":944.95,
        "N2 Node":"4.00",
        "N2 Set-Point":"315.00",
        "N2 Actual Flow":315.15,
        "T Reactor (sliding TC)":"990.00",
        "T Heater 1":338.2,
        "SP Heater 1":"250.00",
        "nan":338.2,
        "nan":250.0,
        "Pressure setpoint":100.01,
        "N2 poisoning set-point":0.0,
        "N2 poisoning Actual flow":"0.00",
        "H2 Uncontrolled flow":"0.00",
        "N2 Uncontrolled flow":"0.00",
        "Inlet calc. flowrate":"28.67",
        "Outlet meas.flowrate":"32.69",
        "Pressure reading":"76.39",
        "T14":"345.91",
        "T13":"347.04",
        "T12":"347.57",
        "T11":"348.73",
        "T10":"350.57",
        "T9":"352.60",
        "T8":"355.99",
        "T7":"360.30",
        "T6":"364.24",
        "T5":"366.14",
        "T4":"365.21",
        "T3":"364.63",
        "T2":"362.01",
        "T1":"359.52",
        "nan":null,
        "Date":"2025-02-22T08:18:08",
        "Stage":57,
        "File":"Exp003_R150_#2674_7969",
        "RT (sec)":19.22,
        "Area":16879,
        "H2":73.0,
        "RT (sec)       _1":21.97,
        "Area           _2":233301,
        "N2":22.555,
        "RT (sec)       _3":38.13,
        "Area           _4":208484,
        "NH3":9.04,
        "Sample name":"Stream 2 - R150"
    },
    {
        "RelativeTime":4185.65,
        "H2 Node":"6.00",
        "H2 Set-Point":"945.00",
        "H2 Actual Flow":945.04,
        "N2 Node":"4.00",
        "N2 Set-Point":"315.00",
        "N2 Actual Flow":315.32,
        "T Reactor (sliding TC)":"990.00",
        "T Heater 1":333.13,
        "SP Heater 1":"250.00",
        "nan":333.13,
        "nan":250.0,
        "Pressure setpoint":100.02,
        "N2 poisoning set-point":0.0,
        "N2 poisoning Actual flow":"0.00",
        "H2 Uncontrolled flow":"0.00",
        "N2 Uncontrolled flow":"0.00",
        "Inlet calc. flowrate":"28.69",
        "Outlet meas.flowrate":"33.25",
        "Pressure reading":"76.39",
        "T14":"340.69",
        "T13":"341.79",
        "T12":"342.32",
        "T11":"343.39",
        "T10":"345.14",
        "T9":"347.08",
        "T8":"350.18",
        "T7":"354.16",
        "T6":"357.87",
        "T5":"359.76",
        "T4":"358.99",
        "T3":"358.60",
        "T2":"356.07",
        "T1":"353.71",
        "nan":null,
        "Date":"2025-02-22T08:23:12",
        "Stage":57,
        "File":"Exp003_R150_#2674_7971",
        "RT (sec)":19.22,
        "Area":17130,
        "H2":74.0,
        "RT (sec)       _1":21.97,
        "Area           _2":234068,
        "N2":22.629,
        "RT (sec)       _3":38.11,
        "Area           _4":191660,
        "NH3":8.31,
        "Sample name":"Stream 2 - R150"
    },
    {
        "RelativeTime":4489.78,
        "H2 Node":"6.00",
        "H2 Set-Point":"945.00",
        "H2 Actual Flow":945.02,
        "N2 Node":"4.00",
        "N2 Set-Point":"315.00",
        "N2 Actual Flow":315.19,
        "T Reactor (sliding TC)":"990.00",
        "T Heater 1":328.06,
        "SP Heater 1":"250.00",
        "nan":328.06,
        "nan":250.0,
        "Pressure setpoint":100.02,
        "N2 poisoning set-point":0.0,
        "N2 poisoning Actual flow":"0.00",
        "H2 Uncontrolled flow":"0.00",
        "N2 Uncontrolled flow":"0.00",
        "Inlet calc. flowrate":"28.68",
        "Outlet meas.flowrate":"33.05",
        "Pressure reading":"76.39",
        "T14":"335.46",
        "T13":"336.46",
        "T12":"336.91",
        "T11":"338.00",
        "T10":"339.61",
        "T9":"341.39",
        "T8":"344.33",
        "T7":"348.08",
        "T6":"351.52",
        "T5":"353.40",
        "T4":"352.73",
        "T3":"352.41",
        "T2":"350.11",
        "T1":"347.91",
        "nan":null,
        "Date":"2025-02-22T08:28:16",
        "Stage":57,
        "File":"Exp003_R150_#2674_7972",
        "RT (sec)":19.22,
        "Area":17196,
        "H2":74.0,
        "RT (sec)       _1":21.97,
        "Area           _2":236593,
        "N2":22.873,
        "RT (sec)       _3":38.14,
        "Area           _4":176722,
        "NH3":7.662,
        "Sample name":"Stream 2 - R150"
    },
    {
        "RelativeTime":4793.72,
        "H2 Node":"6.00",
        "H2 Set-Point":"945.00",
        "H2 Actual Flow":945.02,
        "N2 Node":"4.00",
        "N2 Set-Point":"315.00",
        "N2 Actual Flow":315.5,
        "T Reactor (sliding TC)":"990.00",
        "T Heater 1":323.0,
        "SP Heater 1":"250.00",
        "nan":323.0,
        "nan":250.0,
        "Pressure setpoint":100.01,
        "N2 poisoning set-point":0.0,
        "N2 poisoning Actual flow":"0.00",
        "H2 Uncontrolled flow":"0.00",
        "N2 Uncontrolled flow":"0.00",
        "Inlet calc. flowrate":"28.70",
        "Outlet meas.flowrate":"32.63",
        "Pressure reading":"76.39",
        "T14":"330.25",
        "T13":"331.22",
        "T12":"331.66",
        "T11":"332.63",
        "T10":"334.12",
        "T9":"335.71",
        "T8":"338.42",
        "T7":"341.85",
        "T6":"345.06",
        "T5":"346.93",
        "T4":"346.34",
        "T3":"346.20",
        "T2":"343.94",
        "T1":"341.87",
        "nan":null,
        "Date":"2025-02-22T08:33:20",
        "Stage":57,
        "File":"Exp003_R150_#2674_7974",
        "RT (sec)":19.21,
        "Area":17422,
        "H2":75.0,
        "RT (sec)       _1":21.97,
        "Area           _2":235829,
        "N2":22.799,
        "RT (sec)       _3":38.17,
        "Area           _4":163617,
        "NH3":7.094,
        "Sample name":"Stream 2 - R150"
    },
    {
        "RelativeTime":5097.7,
        "H2 Node":"6.00",
        "H2 Set-Point":"945.00",
        "H2 Actual Flow":945.02,
        "N2 Node":"4.00",
        "N2 Set-Point":"315.00",
        "N2 Actual Flow":315.34,
        "T Reactor (sliding TC)":"990.00",
        "T Heater 1":317.93,
        "SP Heater 1":"250.00",
        "nan":317.93,
        "nan":250.0,
        "Pressure setpoint":100.0,
        "N2 poisoning set-point":0.0,
        "N2 poisoning Actual flow":"0.00",
        "H2 Uncontrolled flow":"0.00",
        "N2 Uncontrolled flow":"0.00",
        "Inlet calc. flowrate":"28.69",
        "Outlet meas.flowrate":"32.94",
        "Pressure reading":"76.39",
        "T14":"325.06",
        "T13":"325.98",
        "T12":"326.40",
        "T11":"327.28",
        "T10":"328.66",
        "T9":"330.15",
        "T8":"332.53",
        "T7":"335.63",
        "T6":"338.53",
        "T5":"340.39",
        "T4":"340.04",
        "T3":"340.05",
        "T2":"338.00",
        "T1":"336.13",
        "nan":null,
        "Date":"2025-02-22T08:38:24",
        "Stage":57,
        "File":"Exp003_R150_#2674_7976",
        "RT (sec)":19.23,
        "Area":17554,
        "H2":75.0,
        "RT (sec)       _1":21.98,
        "Area           _2":237592,
        "N2":22.97,
        "RT (sec)       _3":38.23,
        "Area           _4":145920,
        "NH3":6.327,
        "Sample name":"Stream 2 - R150"
    },
    {
        "RelativeTime":5401.62,
        "H2 Node":"6.00",
        "H2 Set-Point":"945.00",
        "H2 Actual Flow":945.05,
        "N2 Node":"4.00",
        "N2 Set-Point":"315.00",
        "N2 Actual Flow":315.43,
        "T Reactor (sliding TC)":"990.00",
        "T Heater 1":312.87,
        "SP Heater 1":"250.00",
        "nan":312.87,
        "nan":250.0,
        "Pressure setpoint":100.01,
        "N2 poisoning set-point":0.0,
        "N2 poisoning Actual flow":"0.00",
        "H2 Uncontrolled flow":"0.00",
        "N2 Uncontrolled flow":"0.00",
        "Inlet calc. flowrate":"28.69",
        "Outlet meas.flowrate":"32.97",
        "Pressure reading":"76.39",
        "T14":"319.75",
        "T13":"320.61",
        "T12":"320.96",
        "T11":"321.86",
        "T10":"323.06",
        "T9":"324.40",
        "T8":"326.56",
        "T7":"329.38",
        "T6":"332.11",
        "T5":"333.86",
        "T4":"333.62",
        "T3":"333.78",
        "T2":"331.83",
        "T1":"330.12",
        "nan":null,
        "Date":"2025-02-22T08:43:28",
        "Stage":57,
        "File":"Exp003_R150_#2674_7977",
        "RT (sec)":19.23,
        "Area":17680,
        "H2":75.0,
        "RT (sec)       _1":21.98,
        "Area           _2":238347,
        "N2":23.042,
        "RT (sec)       _3":38.25,
        "Area           _4":136663,
        "NH3":5.926,
        "Sample name":"Stream 2 - R150"
    },
    {
        "RelativeTime":5707.81,
        "H2 Node":"6.00",
        "H2 Set-Point":"945.00",
        "H2 Actual Flow":944.99,
        "N2 Node":"4.00",
        "N2 Set-Point":"315.00",
        "N2 Actual Flow":315.47,
        "T Reactor (sliding TC)":"990.00",
        "T Heater 1":307.79,
        "SP Heater 1":"250.00",
        "nan":307.79,
        "nan":250.0,
        "Pressure setpoint":100.02,
        "N2 poisoning set-point":0.0,
        "N2 poisoning Actual flow":"0.00",
        "H2 Uncontrolled flow":"0.00",
        "N2 Uncontrolled flow":"0.00",
        "Inlet calc. flowrate":"28.70",
        "Outlet meas.flowrate":"32.90",
        "Pressure reading":"76.39",
        "T14":"314.55",
        "T13":"315.34",
        "T12":"315.62",
        "T11":"316.35",
        "T10":"317.47",
        "T9":"318.66",
        "T8":"320.69",
        "T7":"323.15",
        "T6":"325.53",
        "T5":"327.24",
        "T4":"327.14",
        "T3":"327.46",
        "T2":"325.63",
        "T1":"324.07",
        "nan":null,
        "Date":"2025-02-22T08:48:34",
        "Stage":57,
        "File":"Exp003_R150_#2674_7979",
        "RT (sec)":19.23,
        "Area":17769,
        "H2":75.0,
        "RT (sec)       _1":21.99,
        "Area           _2":240030,
        "N2":23.205,
        "RT (sec)       _3":38.3,
        "Area           _4":115717,
        "NH3":5.017,
        "Sample name":"Stream 2 - R150"
    },
    {
        "RelativeTime":6009.7,
        "H2 Node":"6.00",
        "H2 Set-Point":"945.00",
        "H2 Actual Flow":945.07,
        "N2 Node":"4.00",
        "N2 Set-Point":"315.00",
        "N2 Actual Flow":315.13,
        "T Reactor (sliding TC)":"990.00",
        "T Heater 1":302.73,
        "SP Heater 1":"250.00",
        "nan":302.73,
        "nan":250.0,
        "Pressure setpoint":100.01,
        "N2 poisoning set-point":0.0,
        "N2 poisoning Actual flow":"0.00",
        "H2 Uncontrolled flow":"0.00",
        "N2 Uncontrolled flow":"0.00",
        "Inlet calc. flowrate":"28.67",
        "Outlet meas.flowrate":"33.00",
        "Pressure reading":"76.39",
        "T14":"309.24",
        "T13":"309.96",
        "T12":"310.24",
        "T11":"310.95",
        "T10":"311.99",
        "T9":"313.02",
        "T8":"314.68",
        "T7":"316.80",
        "T6":"318.76",
        "T5":"320.50",
        "T4":"320.40",
        "T3":"320.84",
        "T2":"319.37",
        "T1":"318.02",
        "nan":null,
        "Date":"2025-02-22T08:53:36",
        "Stage":57,
        "File":"Exp003_R150_#2674_7981",
        "RT (sec)":19.23,
        "Area":17915,
        "H2":76.0,
        "RT (sec)       _1":21.99,
        "Area           _2":241453,
        "N2":23.343,
        "RT (sec)       _3":38.33,
        "Area           _4":99191,
        "NH3":4.301,
        "Sample name":"Stream 2 - R150"
    },
    {
        "RelativeTime":6313.61,
        "H2 Node":"6.00",
        "H2 Set-Point":"945.00",
        "H2 Actual Flow":945.09,
        "N2 Node":"4.00",
        "N2 Set-Point":"315.00",
        "N2 Actual Flow":315.2,
        "T Reactor (sliding TC)":"990.00",
        "T Heater 1":297.66,
        "SP Heater 1":"250.00",
        "nan":297.66,
        "nan":250.0,
        "Pressure setpoint":100.01,
        "N2 poisoning set-point":0.0,
        "N2 poisoning Actual flow":"0.00",
        "H2 Uncontrolled flow":"0.00",
        "N2 Uncontrolled flow":"0.00",
        "Inlet calc. flowrate":"28.68",
        "Outlet meas.flowrate":"32.40",
        "Pressure reading":"76.39",
        "T14":"303.95",
        "T13":"304.67",
        "T12":"304.73",
        "T11":"305.35",
        "T10":"306.39",
        "T9":"307.33",
        "T8":"308.76",
        "T7":"310.55",
        "T6":"312.13",
        "T5":"313.81",
        "T4":"313.88",
        "T3":"314.48",
        "T2":"313.12",
        "T1":"312.00",
        "nan":null,
        "Date":"2025-02-22T08:58:40",
        "Stage":57,
        "File":"Exp003_R150_#2674_7983",
        "RT (sec)":19.24,
        "Area":18068,
        "H2":76.0,
        "RT (sec)       _1":22.0,
        "Area           _2":243036,
        "N2":23.496,
        "RT (sec)       _3":38.38,
        "Area           _4":80374,
        "NH3":3.485,
        "Sample name":"Stream 2 - R150"
    },
    {
        "RelativeTime":6617.67,
        "H2 Node":"6.00",
        "H2 Set-Point":"945.00",
        "H2 Actual Flow":944.94,
        "N2 Node":"4.00",
        "N2 Set-Point":"315.00",
        "N2 Actual Flow":315.17,
        "T Reactor (sliding TC)":"990.00",
        "T Heater 1":292.6,
        "SP Heater 1":"250.00",
        "nan":292.6,
        "nan":250.0,
        "Pressure setpoint":100.03,
        "N2 poisoning set-point":0.0,
        "N2 poisoning Actual flow":"0.00",
        "H2 Uncontrolled flow":"0.00",
        "N2 Uncontrolled flow":"0.00",
        "Inlet calc. flowrate":"28.67",
        "Outlet meas.flowrate":"31.57",
        "Pressure reading":"76.39",
        "T14":"298.73",
        "T13":"299.31",
        "T12":"299.36",
        "T11":"299.87",
        "T10":"300.69",
        "T9":"301.48",
        "T8":"302.77",
        "T7":"304.19",
        "T6":"305.50",
        "T5":"306.98",
        "T4":"307.19",
        "T3":"307.93",
        "T2":"306.75",
        "T1":"305.78",
        "nan":null,
        "Date":"2025-02-22T09:03:44",
        "Stage":57,
        "File":"Exp003_R150_#2674_7984",
        "RT (sec)":19.24,
        "Area":18190,
        "H2":76.0,
        "RT (sec)       _1":22.0,
        "Area           _2":243526,
        "N2":23.543,
        "RT (sec)       _3":38.41,
        "Area           _4":69916,
        "NH3":3.031,
        "Sample name":"Stream 2 - R150"
    },
    {
        "RelativeTime":6921.66,
        "H2 Node":"6.00",
        "H2 Set-Point":"945.00",
        "H2 Actual Flow":944.95,
        "N2 Node":"4.00",
        "N2 Set-Point":"315.00",
        "N2 Actual Flow":315.31,
        "T Reactor (sliding TC)":"990.00",
        "T Heater 1":287.53,
        "SP Heater 1":"250.00",
        "nan":287.53,
        "nan":250.0,
        "Pressure setpoint":100.01,
        "N2 poisoning set-point":0.0,
        "N2 poisoning Actual flow":"0.00",
        "H2 Uncontrolled flow":"0.00",
        "N2 Uncontrolled flow":"0.00",
        "Inlet calc. flowrate":"28.68",
        "Outlet meas.flowrate":"33.06",
        "Pressure reading":"76.40",
        "T14":"293.33",
        "T13":"293.89",
        "T12":"293.93",
        "T11":"294.43",
        "T10":"295.14",
        "T9":"295.75",
        "T8":"296.59",
        "T7":"297.74",
        "T6":"298.65",
        "T5":"300.02",
        "T4":"300.31",
        "T3":"301.20",
        "T2":"300.26",
        "T1":"299.49",
        "nan":null,
        "Date":"2025-02-22T09:08:48",
        "Stage":57,
        "File":"Exp003_R150_#2674_7986",
        "RT (sec)":19.24,
        "Area":18319,
        "H2":76.0,
        "RT (sec)       _1":22.0,
        "Area           _2":246175,
        "N2":23.799,
        "RT (sec)       _3":38.46,
        "Area           _4":50649,
        "NH3":2.196,
        "Sample name":"Stream 2 - R150"
    },
    {
        "RelativeTime":7225.65,
        "H2 Node":"6.00",
        "H2 Set-Point":"945.00",
        "H2 Actual Flow":944.93,
        "N2 Node":"4.00",
        "N2 Set-Point":"315.00",
        "N2 Actual Flow":315.19,
        "T Reactor (sliding TC)":"990.00",
        "T Heater 1":282.46,
        "SP Heater 1":"250.00",
        "nan":282.46,
        "nan":250.0,
        "Pressure setpoint":100.01,
        "N2 poisoning set-point":0.0,
        "N2 poisoning Actual flow":"0.00",
        "H2 Uncontrolled flow":"0.00",
        "N2 Uncontrolled flow":"0.00",
        "Inlet calc. flowrate":"28.68",
        "Outlet meas.flowrate":"32.39",
        "Pressure reading":"76.39",
        "T14":"288.04",
        "T13":"288.60",
        "T12":"288.39",
        "T11":"288.87",
        "T10":"289.48",
        "T9":"289.99",
        "T8":"290.70",
        "T7":"291.50",
        "T6":"291.99",
        "T5":"293.22",
        "T4":"293.35",
        "T3":"294.39",
        "T2":"293.65",
        "T1":"293.15",
        "nan":null,
        "Date":"2025-02-22T09:13:52",
        "Stage":57,
        "File":"Exp003_R150_#2674_7988",
        "RT (sec)":19.21,
        "Area":17755,
        "H2":75.0,
        "RT (sec)       _1":21.99,
        "Area           _2":246155,
        "N2":23.797,
        "RT (sec)       _3":38.52,
        "Area           _4":31093,
        "NH3":1.348,
        "Sample name":"Stream 2 - R150"
    },
    {
        "RelativeTime":7529.67,
        "H2 Node":"6.00",
        "H2 Set-Point":"945.00",
        "H2 Actual Flow":944.96,
        "N2 Node":"4.00",
        "N2 Set-Point":"315.00",
        "N2 Actual Flow":315.39,
        "T Reactor (sliding TC)":"990.00",
        "T Heater 1":277.4,
        "SP Heater 1":"250.00",
        "nan":277.4,
        "nan":250.0,
        "Pressure setpoint":100.01,
        "N2 poisoning set-point":0.0,
        "N2 poisoning Actual flow":"0.00",
        "H2 Uncontrolled flow":"0.00",
        "N2 Uncontrolled flow":"0.00",
        "Inlet calc. flowrate":"28.69",
        "Outlet meas.flowrate":"33.32",
        "Pressure reading":"76.39",
        "T14":"282.82",
        "T13":"283.34",
        "T12":"283.04",
        "T11":"283.39",
        "T10":"283.88",
        "T9":"284.32",
        "T8":"284.86",
        "T7":"285.45",
        "T6":"285.72",
        "T5":"286.65",
        "T4":"286.42",
        "T3":"287.47",
        "T2":"286.86",
        "T1":"286.68",
        "nan":null,
        "Date":"2025-02-22T09:18:56",
        "Stage":57,
        "File":"Exp003_R150_#2674_7989",
        "RT (sec)":19.22,
        "Area":18195,
        "H2":76.0,
        "RT (sec)       _1":21.99,
        "Area           _2":246454,
        "N2":23.826,
        "RT (sec)       _3":38.54,
        "Area           _4":23603,
        "NH3":1.023,
        "Sample name":"Stream 2 - R150"
    },
    {
        "RelativeTime":7833.7,
        "H2 Node":"6.00",
        "H2 Set-Point":"945.00",
        "H2 Actual Flow":945.0,
        "N2 Node":"4.00",
        "N2 Set-Point":"315.00",
        "N2 Actual Flow":315.22,
        "T Reactor (sliding TC)":"990.00",
        "T Heater 1":272.33,
        "SP Heater 1":"250.00",
        "nan":272.33,
        "nan":250.0,
        "Pressure setpoint":100.01,
        "N2 poisoning set-point":0.0,
        "N2 poisoning Actual flow":"0.00",
        "H2 Uncontrolled flow":"0.00",
        "N2 Uncontrolled flow":"0.00",
        "Inlet calc. flowrate":"28.68",
        "Outlet meas.flowrate":"32.21",
        "Pressure reading":"76.39",
        "T14":"277.49",
        "T13":"277.94",
        "T12":"277.64",
        "T11":"277.93",
        "T10":"278.35",
        "T9":"278.70",
        "T8":"279.12",
        "T7":"279.54",
        "T6":"279.56",
        "T5":"280.32",
        "T4":"280.01",
        "T3":"280.81",
        "T2":"280.22",
        "T1":"280.22",
        "nan":null,
        "Date":"2025-02-22T09:24:00",
        "Stage":57,
        "File":"Exp003_R150_#2674_7991",
        "RT (sec)":19.21,
        "Area":17855,
        "H2":75.0,
        "RT (sec)       _1":22.0,
        "Area           _2":247197,
        "N2":23.898,
        "RT (sec)       _3":38.61,
        "Area           _4":9708,
        "NH3":0.421,
        "Sample name":"Stream 2 - R150"
    },
    {
        "RelativeTime":8137.66,
        "H2 Node":"6.00",
        "H2 Set-Point":"945.00",
        "H2 Actual Flow":944.89,
        "N2 Node":"4.00",
        "N2 Set-Point":"315.00",
        "N2 Actual Flow":315.37,
        "T Reactor (sliding TC)":"990.00",
        "T Heater 1":267.27,
        "SP Heater 1":"250.00",
        "nan":267.27,
        "nan":250.0,
        "Pressure setpoint":100.02,
        "N2 poisoning set-point":0.0,
        "N2 poisoning Actual flow":"0.00",
        "H2 Uncontrolled flow":"0.00",
        "N2 Uncontrolled flow":"0.00",
        "Inlet calc. flowrate":"28.69",
        "Outlet meas.flowrate":"33.23",
        "Pressure reading":"76.40",
        "T14":"272.29",
        "T13":"272.67",
        "T12":"272.33",
        "T11":"272.60",
        "T10":"272.98",
        "T9":"273.24",
        "T8":"273.62",
        "T7":"273.94",
        "T6":"273.93",
        "T5":"274.58",
        "T4":"274.22",
        "T3":"274.91",
        "T2":"274.35",
        "T1":"274.36",
        "nan":null,
        "Date":"2025-02-22T09:29:04",
        "Stage":57,
        "File":"Exp003_R150_#2674_7993",
        "RT (sec)":19.22,
        "Area":18482,
        "H2":76.0,
        "RT (sec)       _1":22.01,
        "Area           _2":247397,
        "N2":23.917,
        "RT (sec)       _3":38.63,
        "Area           _4":6114,
        "NH3":0.265,
        "Sample name":"Stream 2 - R150"
    },
    {
        "RelativeTime":8441.66,
        "H2 Node":"6.00",
        "H2 Set-Point":"945.00",
        "H2 Actual Flow":945.06,
        "N2 Node":"4.00",
        "N2 Set-Point":"315.00",
        "N2 Actual Flow":315.23,
        "T Reactor (sliding TC)":"990.00",
        "T Heater 1":262.32,
        "SP Heater 1":"250.00",
        "nan":262.32,
        "nan":250.0,
        "Pressure setpoint":100.01,
        "N2 poisoning set-point":0.0,
        "N2 poisoning Actual flow":"0.00",
        "H2 Uncontrolled flow":"0.00",
        "N2 Uncontrolled flow":"0.00",
        "Inlet calc. flowrate":"28.68",
        "Outlet meas.flowrate":"32.17",
        "Pressure reading":"76.41",
        "T14":"267.23",
        "T13":"267.57",
        "T12":"267.21",
        "T11":"267.44",
        "T10":"267.81",
        "T9":"268.04",
        "T8":"268.39",
        "T7":"268.67",
        "T6":"268.68",
        "T5":"269.26",
        "T4":"268.82",
        "T3":"269.49",
        "T2":"268.89",
        "T1":"268.94",
        "nan":null,
        "Date":"2025-02-22T09:34:08",
        "Stage":57,
        "File":"Exp003_R150_#2674_7994",
        "RT (sec)":19.22,
        "Area":18533,
        "H2":77.0,
        "RT (sec)       _1":22.01,
        "Area           _2":247675,
        "N2":23.944,
        "RT (sec)       _3":38.65,
        "Area           _4":5200,
        "NH3":0.225,
        "Sample name":"Stream 2 - R150"
    },
    {
        "RelativeTime":8745.69,
        "H2 Node":"6.00",
        "H2 Set-Point":"945.00",
        "H2 Actual Flow":944.94,
        "N2 Node":"4.00",
        "N2 Set-Point":"315.00",
        "N2 Actual Flow":315.22,
        "T Reactor (sliding TC)":"990.00",
        "T Heater 1":257.48,
        "SP Heater 1":"250.00",
        "nan":257.48,
        "nan":250.0,
        "Pressure setpoint":100.02,
        "N2 poisoning set-point":0.0,
        "N2 poisoning Actual flow":"0.00",
        "H2 Uncontrolled flow":"0.00",
        "N2 Uncontrolled flow":"0.00",
        "Inlet calc. flowrate":"28.68",
        "Outlet meas.flowrate":"33.04",
        "Pressure reading":"76.40",
        "T14":"262.29",
        "T13":"262.61",
        "T12":"262.29",
        "T11":"262.57",
        "T10":"262.83",
        "T9":"263.09",
        "T8":"263.32",
        "T7":"263.61",
        "T6":"263.55",
        "T5":"264.16",
        "T4":"263.77",
        "T3":"264.47",
        "T2":"263.88",
        "T1":"263.94",
        "nan":null,
        "Date":"2025-02-22T09:39:12",
        "Stage":57,
        "File":"Exp003_R150_#2674_7996",
        "RT (sec)":19.24,
        "Area":18609,
        "H2":77.0,
        "RT (sec)       _1":22.02,
        "Area           _2":249898,
        "N2":24.159,
        "RT (sec)       _3":38.67,
        "Area           _4":3593,
        "NH3":0.156,
        "Sample name":"Stream 2 - R150"
    }
]